conftest.py
firefly/__init__.py
firefly/action.py
firefly/area_detector_overlay.ui
firefly/area_detector_roi.ui
firefly/area_detector_viewer.py
firefly/area_detector_viewer.ui
firefly/beamline_components_rc.py
firefly/bss.py
firefly/bss.ui
firefly/button.py
firefly/component_selector.py
firefly/conftest.py
firefly/controller.py
firefly/detector_list.py
firefly/display.py
firefly/energy.py
firefly/energy.ui
firefly/exceptions.py
firefly/filters.py
firefly/filters.ui
firefly/filters_row.ui
firefly/firefly.qss
firefly/ioc.ui
firefly/iocs.py
firefly/iocs.ui
firefly/ion_chamber.py
firefly/ion_chamber.ui
firefly/kafka_client.py
firefly/kb_mirrors.py
firefly/kb_mirrors.ui
firefly/launcher.py
firefly/log_viewer.ui
firefly/main_window.py
firefly/mirror.py
firefly/mirror.ui
firefly/motor.py
firefly/motor.ui
firefly/pydm_plugin.py
firefly/queue_button.py
firefly/queue_client.py
firefly/robot.py
firefly/robot.ui
firefly/slits.py
firefly/slits.ui
firefly/slits_motor.py
firefly/slits_motor.ui
firefly/splash.png
firefly/status.py
firefly/status.ui
firefly/table.py
firefly/table.ui
firefly/tweak.py
firefly/tweak.ui
firefly/voltmeters.py
firefly/voltmeters.ui
firefly/xrf_detector.py
firefly/xrf_detector.ui
firefly/xrf_plot.ui
firefly/plans/count.py
firefly/plans/count.ui
firefly/plans/grid_scan.py
firefly/plans/grid_scan.ui
firefly/plans/line_scan.py
firefly/plans/line_scan.ui
firefly/plans/move_motor_window.py
firefly/plans/move_motor_window.ui
firefly/plans/regions_display.py
firefly/plans/util.py
firefly/plans/xafs_scan.py
firefly/plans/xafs_scan.ui
firefly/resources/beamline_components.py
firefly/resources/beamline_components.qrc
firefly/resources/filter-empty.png
firefly/resources/filter.png
firefly/resources/insertion_device.png
firefly/resources/kb_mirrors.png
firefly/resources/mirror.png
firefly/resources/monochromator.png
firefly/resources/slits_3d.png
firefly/resources/table.png
firefly/run_browser/__init__.py
firefly/run_browser/client.py
firefly/run_browser/display.py
haven_spc-2025.2.1.dist-info/LICENSE
haven_spc-2025.2.1.dist-info/METADATA
haven_spc-2025.2.1.dist-info/WHEEL
haven_spc-2025.2.1.dist-info/entry_points.txt
haven_spc-2025.2.1.dist-info/top_level.txt
haven_spc-2025.2.1.dist-info/RECORD
