Metadata-Version: 2.2
Name: haven-spc
Version: 2025.2.1
Summary: Tools and GUI for running the spectroscopy group beamlines at the Advanced Photon Source.
Author-email: Mark Wolfman <wolfman@anl.gov>
Project-URL: Homepage, https://haven-spc.readthedocs.io/en/latest/
Project-URL: Bug Tracker, https://github.com/spc-group/haven/issues
Keywords: synchrotron,xray,bluesky
Classifier: Programming Language :: Python :: 3
Classifier: Operating System :: OS Independent
Classifier: Development Status :: 3 - Alpha
Classifier: License :: OSI Approved :: BSD License
Classifier: Topic :: Scientific/Engineering
Classifier: Topic :: System :: Hardware
Requires-Python: >=3.10
License-File: LICENSE
Requires-Dist: aioca
Requires-Dist: aiokafka
Requires-Dist: bluesky
Requires-Dist: ophyd
Requires-Dist: ophyd-async>=0.9.0a2
Requires-Dist: apsbss
Requires-Dist: xraydb
Requires-Dist: mergedeep
Requires-Dist: xrayutilities
Requires-Dist: bluesky-queueserver-api
Requires-Dist: tomlkit
Requires-Dist: apstools
Requires-Dist: ophyd-registry
Requires-Dist: caproto
Requires-Dist: pcdsdevices
Requires-Dist: bluesky-adaptive
Requires-Dist: tiled[client]
Requires-Dist: guarneri>=0.2.0
Provides-Extra: dev
Requires-Dist: black; extra == "dev"
Requires-Dist: pytest; extra == "dev"
Requires-Dist: asynctest; extra == "dev"
Requires-Dist: build; extra == "dev"
Requires-Dist: twine; extra == "dev"
Requires-Dist: time-machine; extra == "dev"
Requires-Dist: pytest-mock; extra == "dev"
Requires-Dist: pytest-qt; extra == "dev"
Requires-Dist: flake8; extra == "dev"
Requires-Dist: pytest-asyncio; extra == "dev"
Requires-Dist: tiled[all]; extra == "dev"
Provides-Extra: gui
Requires-Dist: qtawesome; extra == "gui"
Requires-Dist: pydm<=1.24.1; extra == "gui"
Requires-Dist: pyqtgraph; extra == "gui"
Requires-Dist: qasync; extra == "gui"
Requires-Dist: tiled[all]; extra == "gui"
